django_alexa/__init__.py
django_alexa/alexa.py
django_alexa/apps.py
django_alexa/models.py
django_alexa/serializers.py
django_alexa/urls.py
django_alexa/views.py
django_alexa/api/__init__.py
django_alexa/api/fields.py
django_alexa/internal/__init__.py
django_alexa/internal/exceptions.py
django_alexa/internal/fields.py
django_alexa/internal/intents_schema.py
django_alexa/internal/response_builder.py
django_alexa/internal/validation.py
django_alexa/management/__init__.py
django_alexa/management/base.py
django_alexa/management/commands/__init__.py
django_alexa/management/commands/alexa.py
django_alexa/management/commands/alexa_custom_slots.py
django_alexa/management/commands/alexa_intents.py
django_alexa/management/commands/alexa_utterances.py
django_alexa-0.0.9.dist-info/LICENSE
django_alexa-0.0.9.dist-info/METADATA
django_alexa-0.0.9.dist-info/WHEEL
django_alexa-0.0.9.dist-info/pbr.json
django_alexa-0.0.9.dist-info/top_level.txt
django_alexa-0.0.9.dist-info/RECORD
