Metadata-Version: 2.1
Name: django-alexa
Version: 0.0.9
Summary: Amazon Alexa Skills Kit integration for Django
Home-page: https://github.com/pycontribs/django-alexa
Author: Kyle Rockman
Author-email: kyle.rockman@mac.com
License: MIT
Platform: UNKNOWN
Classifier: Environment :: Console
Classifier: Intended Audience :: Developers
Classifier: Intended Audience :: Information Technology
Classifier: License :: OSI Approved :: Apache Software License
Classifier: Operating System :: OS Independent
Classifier: Programming Language :: Python
Classifier: Programming Language :: Python :: 3 :: Only
Requires-Dist: alabaster (==0.7.12)
Requires-Dist: ansimarkup (==1.4.0)
Requires-Dist: asn1crypto (==0.24.0)
Requires-Dist: babel (==2.6.0)
Requires-Dist: better-exceptions-fork (==0.2.1.post6)
Requires-Dist: certifi (==2018.11.29)
Requires-Dist: cffi (==1.11.5)
Requires-Dist: chardet (==3.0.4)
Requires-Dist: coverage (==4.5.2)
Requires-Dist: coveralls (==1.5.1)
Requires-Dist: cryptography (==2.4.2)
Requires-Dist: django (==2.1.5)
Requires-Dist: djangorestframework (==3.9.0)
Requires-Dist: docopt (==0.6.2)
Requires-Dist: docutils (==0.14)
Requires-Dist: idna (==2.8)
Requires-Dist: imagesize (==1.1.0)
Requires-Dist: jinja2 (==2.10)
Requires-Dist: loguru (==0.2.4)
Requires-Dist: markupsafe (==1.1.0)
Requires-Dist: packaging (==18.0)
Requires-Dist: pbr (==5.1.1)
Requires-Dist: pycparser (==2.19)
Requires-Dist: pycryptodome (==3.7.2)
Requires-Dist: pygments (==2.3.1)
Requires-Dist: pyopenssl (==18.0.0)
Requires-Dist: pyparsing (==2.3.0)
Requires-Dist: pytz (==2018.9)
Requires-Dist: pyversion3 (==0.5.12)
Requires-Dist: requests (==2.21.0)
Requires-Dist: six (==1.12.0)
Requires-Dist: snowballstemmer (==1.2.1)
Requires-Dist: sphinx-rtd-theme (==0.4.2)
Requires-Dist: sphinx (==1.8.3)
Requires-Dist: sphinxcontrib-websupport (==1.1.0)
Requires-Dist: urllib3 (==1.24.1)
Requires-Dist: colorama (==0.4.1) ; (sys_platform == 'win32')
